.DS_Store
knockoffspy/__init__.py
knockoffspy/install.jl
knockoffspy/ko.py
knockoffspy/setup.jl
knockoffspy-0.0.1.dist-info/LICENSE.md
knockoffspy-0.0.1.dist-info/METADATA
knockoffspy-0.0.1.dist-info/WHEEL
knockoffspy-0.0.1.dist-info/top_level.txt
knockoffspy-0.0.1.dist-info/RECORD
