Metadata-Version: 2.1
Name: knockoffspy
Version: 0.0.1
Summary: Variable Selection with Knockoffs in Python
Home-page: https://github.com/biona001/knockoffspy
Author: Benjamin Chu
Author-email: bbchu@stanford.edu
License: MIT
Keywords: knockoff filter knockoffs variable selection feature selection conditional independence group fdr lasso
Platform: UNKNOWN
Classifier: License :: OSI Approved :: MIT License
Classifier: Programming Language :: Python :: 3.6
Classifier: Programming Language :: Python :: 3.7
Classifier: Programming Language :: Python :: 3.8
Classifier: Programming Language :: Python :: 3.9
Requires-Dist: julia (>=0.2)
Requires-Dist: jill
